NikGapps/__init__.py
NikGapps/build_config.py
NikGapps/cache.py
NikGapps/config_upload.py
NikGapps/copy_repos.py
NikGapps/main.py
NikGapps/overlay_control.py
NikGapps/test.py
NikGapps/build/Build.py
NikGapps/build/NikGappsManager.py
NikGapps/build/NikGappsOverlays.py
NikGapps/build/PackageConstants.py
NikGapps/build/Release.py
NikGapps/build/__init__.py
NikGapps/config/NikGappsConfig.py
NikGapps/config/__init__.py
NikGapps/helper/AppSet.py
NikGapps/helper/Args.py
NikGapps/helper/Assets.py
NikGapps/helper/Config.py
NikGapps/helper/ConfigObj.py
NikGapps/helper/Package.py
NikGapps/helper/__init__.py
NikGapps/helper/assets/addon.sh
NikGapps/helper/assets/appsets.json
NikGapps/helper/assets/changelogs.yaml
NikGapps/helper/assets/config_versions.json
NikGapps/helper/assets/customize.sh
NikGapps/helper/assets/debloater.config
NikGapps/helper/assets/functions.sh
NikGapps/helper/assets/gofile.sh
NikGapps/helper/assets/header.sh
NikGapps/helper/assets/installer.sh
NikGapps/helper/assets/magisk-update-binary.sh
NikGapps/helper/assets/module.prop
NikGapps/helper/assets/mount.sh
NikGapps/helper/assets/mtg_mount.sh
NikGapps/helper/assets/nikgapps.config
NikGapps/helper/assets/nikgapps_functions.sh
NikGapps/helper/assets/packages.json
NikGapps/helper/assets/uninstaller.sh
NikGapps/helper/assets/unmount.sh
NikGapps/helper/compression/CompOps.py
NikGapps/helper/compression/Export.py
NikGapps/helper/compression/__init__.py
NikGapps/helper/git/TestGit.py
NikGapps/helper/git/__init__.py
NikGapps/helper/overlay/ApkMetaInfo.py
NikGapps/helper/overlay/Bool.py
NikGapps/helper/overlay/Library.py
NikGapps/helper/overlay/Manifest.py
NikGapps/helper/overlay/Overlay.py
NikGapps/helper/overlay/Resources.py
NikGapps/helper/overlay/String.py
NikGapps/helper/overlay/StringArray.py
NikGapps/helper/overlay/__init__.py
nikgapps-3.83.dist-info/licenses/LICENSE
nikgapps-3.83.dist-info/METADATA
nikgapps-3.83.dist-info/WHEEL
nikgapps-3.83.dist-info/entry_points.txt
nikgapps-3.83.dist-info/top_level.txt
nikgapps-3.83.dist-info/RECORD
