Metadata-Version: 2.4
Name: NikGapps
Version: 3.83
Summary: A short description of your project
Home-page: https://github.com/nikgapps/project
Author: Nikhil Menghani
Author-email: nikgapps@gmail.com
Classifier: Programming Language :: Python :: 3
Classifier: License :: OSI Approved :: MIT License
Requires-Python: >=3.12
License-File: LICENSE
Requires-Dist: colorama~=0.4.6
Requires-Dist: pytz~=2025.2
Requires-Dist: requests~=2.32.5
Requires-Dist: PyYAML~=6.0.2
Requires-Dist: psutil~=7.0.0
Requires-Dist: setuptools~=80.9.0
Requires-Dist: pexpect~=4.9.0
Requires-Dist: GitPython~=3.1.45
Requires-Dist: PyGithub~=2.8.1
Requires-Dist: python-gitlab~=6.3.0
Requires-Dist: cryptography~=45.0.7
Requires-Dist: python-dotenv~=1.1.1
Requires-Dist: niklibrary~=0.50
Dynamic: author
Dynamic: author-email
Dynamic: classifier
Dynamic: description
Dynamic: description-content-type
Dynamic: home-page
Dynamic: license-file
Dynamic: requires-dist
Dynamic: requires-python
Dynamic: summary
